ocrd_pc_segmentation/__init__.py
ocrd_pc_segmentation/cli.py
ocrd_pc_segmentation/ocrd-tool.json
ocrd_pc_segmentation/ocrd_segmentation.py
ocrd_pc_segmentation/dta2-model/model.h5
ocrd_pc_segmentation/lgt-model/model.h5
ocrd_pc_segmentation-0.2.3.data/data/requirements.txt
ocrd_pc_segmentation-0.2.3.dist-info/LICENSE
ocrd_pc_segmentation-0.2.3.dist-info/METADATA
ocrd_pc_segmentation-0.2.3.dist-info/WHEEL
ocrd_pc_segmentation-0.2.3.dist-info/entry_points.txt
ocrd_pc_segmentation-0.2.3.dist-info/top_level.txt
ocrd_pc_segmentation-0.2.3.dist-info/RECORD
