Metadata-Version: 2.1
Name: ocrd-pc-segmentation
Version: 0.2.3
Summary: pixel-classifier based page segmentation
Home-page: https://github.com/ocr-d-modul-2-segmentierung/ocrd-pixelclassifier-segmentation
Author: Alexander Gehrke, Christian Reul, Christoph Wick
Author-email: alexander.gehrke@uni-wuerzburg.de, christian.reul@uni-wuerzburg.de, christoph.wick@uni-wuerzburg.de
License: UNKNOWN
Platform: UNKNOWN
Classifier: Programming Language :: Python :: 3
Classifier: License :: OSI Approved :: Apache Software License
Classifier: Topic :: Scientific/Engineering :: Image Recognition
Requires-Dist: ocrd (>=2.0.0a1)
Requires-Dist: ocr4all-pixel-classifier (~=0.6)
Requires-Dist: numpy
Provides-Extra: tf_cpu
Requires-Dist: ocr4all-pixel-classifier[tf_cpu] (~=0.4.0) ; extra == 'tf_cpu'
Provides-Extra: tf_gpu
Requires-Dist: ocr4all-pixel-classifier[tf_gpu] (~=0.4.0) ; extra == 'tf_gpu'
